deepthoughthttp/DTFile.py
deepthoughthttp/DTHTTPRequest.py
deepthoughthttp/DTSession.py
deepthoughthttp/__init__.py
deepthoughthttp-1.0.0.dist-info/DESCRIPTION.rst
deepthoughthttp-1.0.0.dist-info/METADATA
deepthoughthttp-1.0.0.dist-info/RECORD
deepthoughthttp-1.0.0.dist-info/WHEEL
deepthoughthttp-1.0.0.dist-info/metadata.json
deepthoughthttp-1.0.0.dist-info/top_level.txt
