Metadata-Version: 2.0
Name: deepthoughthttp
Version: 1.0.0
Summary: Python implementation of the Deep Thought Library
Home-page: https://github.com/expressive-analytics/deep-thought.py
Author: Blake Anderson
Author-email: blake@expressiveanalytics.com
License: MIT
Keywords: orm api-centered deep-thought
Platform: UNKNOWN
Classifier: Development Status :: 4 - Beta
Classifier: Intended Audience :: Developers
Classifier: Topic :: Software Development :: Libraries
Classifier: License :: OSI Approved :: MIT License
Classifier: Programming Language :: Python :: 2
Classifier: Programming Language :: Python :: 2.6
Classifier: Programming Language :: Python :: 2.7
Classifier: Programming Language :: Python :: 3
Classifier: Programming Language :: Python :: 3.3
Classifier: Programming Language :: Python :: 3.4
Classifier: Programming Language :: Python :: 3.5
Requires-Dist: deepthought
Requires-Dist: requests
Provides-Extra: dev
Provides-Extra: test
